pyxel/__init__.py
pyxel/bspline_patch.py
pyxel/bspline_routines.py
pyxel/camera.py
pyxel/dic.py
pyxel/exportpixmap.py
pyxel/image.py
pyxel/levelset.py
pyxel/material.py
pyxel/mesh.py
pyxel/mesher.py
pyxel/meshparser.py
pyxel/utils.py
pyxel/vtktools.py
pyxel_dic-2025.2.17.dist-info/METADATA
pyxel_dic-2025.2.17.dist-info/WHEEL
pyxel_dic-2025.2.17.dist-info/top_level.txt
pyxel_dic-2025.2.17.dist-info/RECORD
