Metadata-Version: 2.1
Name: pyxel-dic
Version: 2025.2.17
Summary: Finite Element (FE) Digital Image/Volume Correlation (DIC/DVC) library for experimental mechanics
Home-page: https://github.com/jcpassieux/pyxel
Author: Jean-Charles Passieux
Author-email: JC Passieux <jc.passieux@gmail.com>
License: 
Project-URL: Homepage, https://github.com/jcpassieux/pyxel
Project-URL: Bug Tracker, https://github.com/jcpassieux/pyxel/issues
Classifier: Programming Language :: Python :: 3
Classifier: Operating System :: OS Independent
Requires-Python: >=3.7
Requires-Dist: numpy
Requires-Dist: scipy
Requires-Dist: matplotlib
Requires-Dist: meshio
Requires-Dist: opencv-python
Requires-Dist: gmsh
Requires-Dist: scikit-image
Requires-Dist: interpylate
Requires-Dist: cgal
